sage/service/__init__.py
sage/service/py.typed
sage/service/api/__init__.py
sage/service/api/graph_api.py
sage/service/api/kv_api.py
sage/service/api/memory_api.py
sage/service/api/vdb_api.py
sage/service/examples/api_usage_tutorial.py
sage/service/examples/dag_microservices_demo.py
sage/service/examples/microservices_demo.py
sage/service/examples/microservices_integration_demo.py
sage/service/examples/microservices_registration_demo.py
sage/service/services/graph/__init__.py
sage/service/services/graph/graph_index.py
sage/service/services/graph/graph_service.py
sage/service/services/graph/examples/graph_demo.py
sage/service/services/graph/search_engine/__init__.py
sage/service/services/graph/search_engine/base_graph_index.py
sage/service/services/kv/__init__.py
sage/service/services/kv/kv_service.py
sage/service/services/kv/examples/kv_demo.py
sage/service/services/kv/search_engine/__init__.py
sage/service/services/kv/search_engine/base_kv_index.py
sage/service/services/kv/search_engine/bm25s_index.py
sage/service/services/memory/__init__.py
sage/service/services/memory/memory_service.py
sage/service/services/memory/examples/dag_microservices_demo.py
sage/service/services/memory/examples/memory_demo.py
sage/service/services/memory/memory_collection/base_collection.py
sage/service/services/memory/memory_collection/graph_collection.py
sage/service/services/memory/memory_collection/kv_collection.py
sage/service/services/memory/memory_collection/vdb_collection.py
sage/service/services/memory/utils/__init__.py
sage/service/services/memory/utils/path_utils.py
sage/service/services/vdb/__init__.py
sage/service/services/vdb/vdb_service.py
sage/service/services/vdb/examples/vdb_demo.py
sage/service/services/vdb/search_engine/__init__.py
sage/service/services/vdb/search_engine/base_vdb_index.py
sage/service/services/vdb/search_engine/faiss_index.py
sage/service/utils/__init__.py
sage/service/utils/embedding/__init__.py
sage/service/utils/embedding/_cohere.py
intsage_middleware-1.0.0.dist-info/METADATA
intsage_middleware-1.0.0.dist-info/WHEEL
intsage_middleware-1.0.0.dist-info/top_level.txt
intsage_middleware-1.0.0.dist-info/RECORD
