Metadata-Version: 2.4
Name: intsage-middleware
Version: 1.0.0
Summary: SAGE Framework - 中间件组件 (包含 LLM 中间件服务)
Author-email: IntelliStream Team <intellistream@outlook.com>
License: MIT
Project-URL: Homepage, https://github.com/intellistream/SAGE
Project-URL: Repository, https://github.com/intellistream/SAGE.git
Project-URL: Documentation, https://intellistream.github.io/SAGE-Pub/
Project-URL: Issues, https://github.com/intellistream/SAGE/issues
Keywords: framework,service,middleware,rag,intellistream,ai,reasoning,llm,data,dataflow,sage,api,ml
Classifier: Development Status :: 4 - Beta
Classifier: Intended Audience :: Developers
Classifier: Intended Audience :: Science/Research
Classifier: License :: OSI Approved :: MIT License
Classifier: Operating System :: OS Independent
Classifier: Programming Language :: Python :: 3
Classifier: Programming Language :: Python :: 3.10
Classifier: Programming Language :: Python :: 3.11
Classifier: Programming Language :: Python :: 3.12
Classifier: Topic :: Scientific/Engineering :: Artificial Intelligence
Classifier: Topic :: Software Development :: Libraries :: Python Modules
Classifier: Topic :: System :: Distributed Computing
Requires-Python: >=3.10
Requires-Dist: intellistream-sage-kernel==1.0.0
Requires-Dist: python-jose==3.5.0
Requires-Dist: passlib==1.7.4
Requires-Dist: celery==5.5.3
Requires-Dist: flower==2.0.1
Requires-Dist: openai==1.98.0
Requires-Dist: ollama==0.5.1
Requires-Dist: zhipuai==2.1.5.20250801
Requires-Dist: cohere==5.16.1
Requires-Dist: transformers==4.54.1
Requires-Dist: tokenizers==0.21.4
Requires-Dist: vllm==0.1.2
Requires-Dist: faiss-cpu==1.9.0
Requires-Dist: bm25s==0.2.13
Requires-Dist: rank-bm25==0.2.2
Requires-Dist: PyStemmer==3.0.0
Requires-Dist: aiohttp==3.12.15
Requires-Dist: frozenlist==1.7.0
Requires-Dist: httpx==0.28.1
Requires-Dist: certifi==2025.8.3
Requires-Dist: feedparser==6.0.11
Requires-Dist: accelerate==1.9.0
Requires-Dist: sentence-transformers==3.1.1
Requires-Dist: InstructorEmbedding==1.0.1
Requires-Dist: huggingface-hub==0.34.3
Requires-Dist: peft==0.17.0
Requires-Dist: numpy==2.2.6
Requires-Dist: scipy==1.15.3
Requires-Dist: fastapi==0.115.12
Requires-Dist: uvicorn==0.34.3
Requires-Dist: pydantic
Requires-Dist: pyyaml==6.0.2
Provides-Extra: database
Requires-Dist: sqlalchemy==2.0.32; extra == "database"
Requires-Dist: alembic==1.13.2; extra == "database"
Requires-Dist: asyncpg==0.30.0; extra == "database"
Requires-Dist: pymongo[srv]==4.8.0; extra == "database"
Provides-Extra: messagequeue
Requires-Dist: celery==5.5.3; extra == "messagequeue"
Requires-Dist: redis==5.2.1; extra == "messagequeue"
Requires-Dist: kafka-python==2.0.3; extra == "messagequeue"
Requires-Dist: pika==1.3.2; extra == "messagequeue"
Provides-Extra: monitoring
Requires-Dist: prometheus-client==0.21.1; extra == "monitoring"
Requires-Dist: structlog==24.4.0; extra == "monitoring"
Requires-Dist: sentry-sdk[fastapi]==2.18.0; extra == "monitoring"
Provides-Extra: llm
Requires-Dist: anthropic==0.34.2; extra == "llm"
Requires-Dist: google-generativeai==0.8.3; extra == "llm"
Requires-Dist: cohere==5.16.2; extra == "llm"
Requires-Dist: langchain==0.3.18; extra == "llm"
Requires-Dist: llama-index==0.11.33; extra == "llm"
Provides-Extra: full
Requires-Dist: sage-middleware[database,llm,messagequeue,monitoring,websocket]; extra == "full"
Provides-Extra: testing
Requires-Dist: pytest==8.3.4; extra == "testing"
Requires-Dist: pytest-asyncio==0.25.0; extra == "testing"
Requires-Dist: pytest-cov==6.0.0; extra == "testing"
Requires-Dist: pytest-benchmark==4.0.0; extra == "testing"
Requires-Dist: testcontainers==4.8.2; extra == "testing"
Requires-Dist: pytest-mock==3.14.0; extra == "testing"
